{"assets":[{"id":"comp_2","layers":[{"ddd":0,"ind":0,"ty":4,"nm":"head ","parent":1,"ks":{"o":{"k":100},"r":{"k":[{"i":{"x":[0.667],"y":[1]},"o":{"x":[0.333],"y":[0]},"n":["0p667_1_0p333_0"],"t":0,"s":[0],"e":[-3]},{"i":{"x":[0.667],"y":[1]},"o":{"x":[0.333],"y":[0]},"n":["0p667_1_0p333_0"],"t":15,"s":[-3],"e":[0]},{"i":{"x":[0.667],"y":[1]},"o":{"x":[0.333],"y":[0]},"n":["0p667_1_0p333_0"],"t":30,"s":[0],"e":[-3]},{"i":{"x":[0.667],"y":[1]},"o":{"x":[0.333],"y":[0]},"n":["0p667_1_0p333_0"],"t":46,"s":[-3],"e":[0]},{"t":59.0000024031193}]},"p":{"k":[{"i":{"x":0.667,"y":1},"o":{"x":0.333,"y":0},"n":"0p667_1_0p333_0","t":0,"s":[15.5,21.444,0],"e":[15.5,15.444,0],"to":[0,-1,0],"ti":[0,0,0]},{"i":{"x":0.667,"y":1},"o":{"x":0.333,"y":0},"n":"0p667_1_0p333_0","t":15,"s":[15.5,15.444,0],"e":[15.5,21.444,0],"to":[0,0,0],"ti":[0,0,0]},{"i":{"x":0.667,"y":1},"o":{"x":0.333,"y":0},"n":"0p667_1_0p333_0","t":30,"s":[15.5,21.444,0],"e":[15.5,15.444,0],"to":[0,0,0],"ti":[0,0,0]},{"i":{"x":0.667,"y":1},"o":{"x":0.333,"y":0},"n":"0p667_1_0p333_0","t":46,"s":[15.5,15.444,0],"e":[15.5,21.444,0],"to":[0,0,0],"ti":[0,0,0]},{"t":59.0000024031193}]},"a":{"k":[24.712,127.467,0]},"s":{"k":[100,100,100]}},"shapes":[{"ty":"gr","it":[{"ind":0,"ty":"sh","closed":true,"ks":{"k":{"i":[[0.108,0.353],[5.883,0.819],[1.049,-0.95],[-0.577,-0.227],[-4.325,-0.001],[-2.744,2.827]],"o":[[-3.096,1.875],[-7.168,-0.999],[-0.254,0.23],[4.026,1.582],[2.388,0],[-0.137,-0.334]],"v":[[17.268,-0.311],[-2.055,1.754],[-17.382,-2.97],[-9.47,1.53],[3.196,3.921],[17.636,0.719]]}},"nm":"Path 1"},{"ty":"fl","fillEnabled":true,"c":{"k":[0,159,139,255]},"o":{"k":100},"nm":"Fill 1"},{"ty":"tr","p":{"k":[{"i":{"x":0.667,"y":1},"o":{"x":0.333,"y":0},"n":"0p667_1_0p333_0","t":0,"s":[69.974,102.353],"e":[68.474,102.353],"to":[-0.25,0],"ti":[0,0]},{"i":{"x":0.667,"y":1},"o":{"x":0.333,"y":0},"n":"0p667_1_0p333_0","t":15,"s":[68.474,102.353],"e":[69.974,102.353],"to":[0,0],"ti":[0,0]},{"i":{"x":0.667,"y":1},"o":{"x":0.333,"y":0},"n":"0p667_1_0p333_0","t":30,"s":[69.974,102.353],"e":[68.474,102.353],"to":[0,0],"ti":[0,0]},{"i":{"x":0.667,"y":1},"o":{"x":0.333,"y":0},"n":"0p667_1_0p333_0","t":46,"s":[68.474,102.353],"e":[69.974,102.353],"to":[0,0],"ti":[-0.25,0]},{"t":59.0000024031193}]},"a":{"k":[0,0]},"s":{"k":[100,100]},"r":{"k":0},"o":{"k":100},"sk":{"k":0},"sa":{"k":0}}],"nm":"Group 1"},{"ty":"gr","it":[{"ind":0,"ty":"sh","closed":true,"ks":{"k":{"i":[[0,0],[0,0],[0,0],[0,0]],"o":[[0,0],[0,0],[0,0],[0,0]],"v":[[-3.142,-5.647],[-3.142,1.312],[3.142,5.647],[2.427,-2.168]]}},"nm":"Path 1"},{"ty":"fl","fillEnabled":true,"c":{"k":[0,159,139,255]},"o":{"k":100},"nm":"Fill 1"},{"ty":"tr","p":{"k":[{"i":{"x":0.833,"y":0.833},"o":{"x":0.167,"y":0.167},"n":"0p833_0p833_0p167_0p167","t":0,"s":[91.831,41.096],"e":[92.831,37.596],"to":[0.16666667163372,-0.58333331346512],"ti":[0,0]},{"i":{"x":0.833,"y":0.833},"o":{"x":0.167,"y":0.167},"n":"0p833_0p833_0p167_0p167","t":15,"s":[92.831,37.596],"e":[91.831,41.096],"to":[0,0],"ti":[0.16666667163372,0]},{"i":{"x":0.833,"y":0.833},"o":{"x":0.167,"y":0.167},"n":"0p833_0p833_0p167_0p167","t":30,"s":[91.831,41.096],"e":[91.831,37.596],"to":[-0.16666667163372,0],"ti":[0,0]},{"i":{"x":0.833,"y":0.833},"o":{"x":0.167,"y":0.167},"n":"0p833_0p833_0p167_0p167","t":46,"s":[91.831,37.596],"e":[91.831,41.096],"to":[0,0],"ti":[0,-0.58333331346512]},{"t":59.0000024031193}]},"a":{"k":[0,0]},"s":{"k":[100,100]},"r":{"k":0},"o":{"k":100},"sk":{"k":0},"sa":{"k":0}}],"nm":"Group 2"},{"ty":"gr","it":[{"ind":0,"ty":"sh","closed":true,"ks":{"k":{"i":[[0,0],[0,0],[0,0],[0,0]],"o":[[0,0],[0,0],[0,0],[0,0]],"v":[[-7.958,-0.803],[-7.958,3.479],[7.958,1.339],[4.924,-3.479]]}},"nm":"Path 1"},{"ty":"fl","fillEnabled":true,"c":{"k":[0,159,139,255]},"o":{"k":100},"nm":"Fill 1"},{"ty":"tr","p":{"k":[{"i":{"x":0.833,"y":0.833},"o":{"x":0.167,"y":0.167},"n":"0p833_0p833_0p167_0p167","t":0,"s":[68.128,38.928],"e":[64.628,36.428],"to":[-0.58333331346512,-0.41666665673256],"ti":[0.08333333581686,0]},{"i":{"x":0.833,"y":0.833},"o":{"x":0.167,"y":0.167},"n":"0p833_0p833_0p167_0p167","t":15,"s":[64.628,36.428],"e":[67.628,38.928],"to":[-0.08333333581686,0],"ti":[-0.08333333581686,0]},{"i":{"x":0.833,"y":0.833},"o":{"x":0.167,"y":0.167},"n":"0p833_0p833_0p167_0p167","t":30,"s":[67.628,38.928],"e":[65.128,36.428],"to":[0.08333333581686,0],"ti":[0,0]},{"i":{"x":0.833,"y":0.833},"o":{"x":0.167,"y":0.167},"n":"0p833_0p833_0p167_0p167","t":46,"s":[65.128,36.428],"e":[67.628,38.928],"to":[0,0],"ti":[-0.41666665673256,-0.41666665673256]},{"t":59.0000024031193}]},"a":{"k":[0,0]},"s":{"k":[100,100]},"r":{"k":0},"o":{"k":100},"sk":{"k":0},"sa":{"k":0}}],"nm":"Group 3"},{"ty":"gr","it":[{"ind":0,"ty":"sh","closed":true,"ks":{"k":{"i":[[0.473,5.779],[0.001,0.018],[0.051,0.551],[0.403,-3.878],[-3.662,0.664],[-0.194,0.096]],"o":[[-0.001,-0.018],[-0.048,-0.551],[-0.624,0.847],[0,0],[0.226,-0.041],[-0.836,-5.736]],"v":[[0.072,-8.212],[0.073,-8.263],[-0.084,-9.917],[-1.681,-3.153],[1.517,9.253],[2.145,9.045]]}},"nm":"Path 1"},{"ty":"fl","fillEnabled":true,"c":{"k":[0,159,139,255]},"o":{"k":100},"nm":"Fill 1"},{"ty":"tr","p":{"k":[{"i":{"x":0.667,"y":1},"o":{"x":0.333,"y":0},"n":"0p667_1_0p333_0","t":0,"s":[95.647,64.148],"e":[93.647,64.148],"to":[-0.33333334326744,0],"ti":[0,0]},{"i":{"x":0.667,"y":1},"o":{"x":0.333,"y":0},"n":"0p667_1_0p333_0","t":15,"s":[93.647,64.148],"e":[95.647,64.148],"to":[0,0],"ti":[0,0]},{"i":{"x":0.667,"y":1},"o":{"x":0.333,"y":0},"n":"0p667_1_0p333_0","t":30,"s":[95.647,64.148],"e":[93.647,64.148],"to":[0,0],"ti":[0,0]},{"i":{"x":0.667,"y":1},"o":{"x":0.333,"y":0},"n":"0p667_1_0p333_0","t":46,"s":[93.647,64.148],"e":[95.647,64.148],"to":[0,0],"ti":[-0.33333334326744,0]},{"t":58.0000023623884}]},"a":{"k":[0,0]},"s":{"k":[{"i":{"x":[0.667,0.667],"y":[0.667,1]},"o":{"x":[0.333,0.333],"y":[0.333,0]},"n":["0p667_0p667_0p333_0p333","0p667_1_0p333_0"],"t":15,"s":[100,100],"e":[100,14],"__fnct":[null,null]},{"i":{"x":[0.667,0.667],"y":[0.667,1]},"o":{"x":[0.333,0.333],"y":[0.333,0]},"n":["0p667_0p667_0p333_0p333","0p667_1_0p333_0"],"t":30,"s":[100,14],"e":[100,100],"__fnct":[null,null]},{"t":46.0000018736184}]},"r":{"k":0},"o":{"k":100},"sk":{"k":0},"sa":{"k":0}}],"nm":"Group 4"},{"ty":"gr","it":[{"ind":0,"ty":"sh","closed":true,"ks":{"k":{"i":[[2.953,-14.453],[-5.388,0.535],[0.535,3.747]],"o":[[0,0],[5.389,-0.536],[-0.535,-3.747]],"v":[[-3.971,0.535],[-0.001,13.383],[4.318,0.535]]}},"nm":"Path 1"},{"ty":"fl","fillEnabled":true,"c":{"k":[0,159,139,255]},"o":{"k":100},"nm":"Fill 1"},{"ty":"tr","p":{"k":[{"i":{"x":0.667,"y":1},"o":{"x":0.333,"y":0},"n":"0p667_1_0p333_0","t":0,"s":[70.446,59.539],"e":[68.446,59.539],"to":[-0.33333334326744,0],"ti":[0,0]},{"i":{"x":0.667,"y":1},"o":{"x":0.333,"y":0},"n":"0p667_1_0p333_0","t":15,"s":[68.446,59.539],"e":[70.446,59.539],"to":[0,0],"ti":[0,0]},{"i":{"x":0.667,"y":1},"o":{"x":0.333,"y":0},"n":"0p667_1_0p333_0","t":30,"s":[70.446,59.539],"e":[68.446,59.539],"to":[0,0],"ti":[0,0]},{"i":{"x":0.667,"y":1},"o":{"x":0.333,"y":0},"n":"0p667_1_0p333_0","t":46,"s":[68.446,59.539],"e":[70.446,59.539],"to":[0,0],"ti":[-0.33333334326744,0]},{"t":59.0000024031193}]},"a":{"k":[0,0]},"s":{"k":[{"i":{"x":[0.667,0.667],"y":[0.667,0.667]},"o":{"x":[0.167,0.167],"y":[0.167,0.167]},"n":["0p667_0p667_0p167_0p167","0p667_0p667_0p167_0p167"],"t":0,"s":[100,100],"e":[100,100],"__fnct":[null,null]},{"i":{"x":[0.667,0.667],"y":[0.667,1]},"o":{"x":[0.333,0.333],"y":[0.333,0]},"n":["0p667_0p667_0p333_0p333","0p667_1_0p333_0"],"t":15,"s":[100,100],"e":[100,14],"__fnct":[null,null]},{"i":{"x":[0.667,0.667],"y":[0.667,1]},"o":{"x":[0.333,0.333],"y":[0.333,0]},"n":["0p667_0p667_0p333_0p333","0p667_1_0p333_0"],"t":30,"s":[100,14],"e":[100,100],"__fnct":[null,null]},{"t":46.0000018736184}]},"r":{"k":0},"o":{"k":100},"sk":{"k":0},"sa":{"k":0}}],"nm":"Group 5"},{"ty":"gr","it":[{"ind":0,"ty":"sh","closed":true,"ks":{"k":{"i":[[0,0],[0,0],[22.616,2.714],[2.735,-0.375],[0,0]],"o":[[0,0],[-22.455,4.084],[-2.55,-0.425],[1.045,4.723],[9.1,0.535]],"v":[[39.037,-0.314],[39.053,-0.563],[-30.928,-5.508],[-39.053,-6.27],[4.242,6.11]]}},"nm":"Path 1"},{"ty":"fl","fillEnabled":true,"c":{"k":[0,159,139,255]},"o":{"k":100},"nm":"Fill 1"},{"ty":"tr","p":{"k":[52.501,129.039]},"a":{"k":[0,0]},"s":{"k":[100,100]},"r":{"k":0},"o":{"k":100},"sk":{"k":0},"sa":{"k":0}}],"nm":"Group 6"},{"ty":"gr","it":[{"ind":0,"ty":"sh","closed":true,"ks":{"k":{"i":[[-5.619,4.37],[-1.59,-3.914],[0.712,1.424],[0.087,-1.613],[-0.101,-0.303],[0,0],[0,0],[0.14,0.345],[1.549,-1.936],[0,0]],"o":[[3.442,-2.869],[0.087,-1.613],[0.712,1.424],[0.14,0.345],[0,0],[0,0],[-0.101,-0.303],[-0.142,2.631],[0,0],[-4.995,-3.122]],"v":[[-35.953,-4.064],[-26.953,3.074],[-27.837,-1.567],[-26.953,3.074],[-26.589,4.052],[-26.589,3.428],[-26.589,4.052],[-26.953,3.074],[-29.71,10.296],[-32.208,10.296]]}},"nm":"Path 1"},{"ind":1,"ty":"sh","closed":true,"ks":{"k":{"i":[[-2.55,-0.425],[-22.455,4.084],[0,0],[0,0],[0.535,8.03],[0.667,6.875],[17.573,-5.272],[-1.873,-4.995],[1.248,-10.613],[11.863,-4.995],[1.249,-3.746],[0.625,-2.498],[-1.249,-4.37],[-3.746,-3.121],[0.624,-0.624],[2.667,1.25],[-0.751,-2.503],[-1.133,-5.12]],"o":[[22.616,2.714],[0,0],[0,0],[0,0],[-0.438,-6.565],[-18.74,1.851],[-3.121,1.248],[4.371,8.74],[-5.619,-9.989],[-3.121,1.249],[0,2.497],[-0.624,4.994],[1.873,4.37],[0.624,1.249],[-2.818,0.651],[0.659,2.889],[2.506,8.354],[2.735,-0.375]],"v":[[-31.016,47.132],[38.966,52.077],[41.627,11.106],[47.191,8.965],[43.233,-19.407],[40.259,-52.293],[-14.727,-50.889],[-12.854,-37.778],[-12.229,-7.186],[-39.076,-22.794],[-45.318,-13.429],[-46.568,-6.561],[-45.318,7.174],[-36.577,17.163],[-38.451,19.036],[-46.678,17.431],[-44.559,25.56],[-39.139,46.37]]}},"nm":"Path 2"},{"ty":"mm","mm":1,"nm":"Merge Paths 1"},{"ty":"fl","fillEnabled":true,"c":{"k":[236,216,47,255]},"o":{"k":100},"nm":"Fill 1"},{"ty":"tr","p":{"k":[52.588,76.4]},"a":{"k":[0,0]},"s":{"k":[100,100]},"r":{"k":0},"o":{"k":100},"sk":{"k":0},"sa":{"k":0}}],"nm":"Group 7"},{"ty":"gr","it":[{"ind":0,"ty":"sh","closed":true,"ks":{"k":{"i":[[3.442,-2.869],[-4.995,-3.122],[0,0],[-0.142,2.631]],"o":[[-5.619,4.37],[0,0],[1.549,-1.936],[-1.59,-3.914]],"v":[[-1.691,-5.746],[2.055,8.615],[4.553,8.615],[7.31,1.392]]}},"nm":"Path 1"},{"ty":"fl","fillEnabled":true,"c":{"k":[0,159,139,255]},"o":{"k":100},"nm":"Fill 1"},{"ty":"tr","p":{"k":[18.325,78.081]},"a":{"k":[0,0]},"s":{"k":[100,100]},"r":{"k":0},"o":{"k":100},"sk":{"k":0},"sa":{"k":0}}],"nm":"Group 8"},{"ty":"gr","it":[{"ind":0,"ty":"sh","closed":true,"ks":{"k":{"i":[[1.606,4.282],[14.989,2.141],[0,0],[0,0],[0,0],[0,0],[0,0],[0,0],[1.025,-13.918],[-3.57,-15.653],[-2.818,0.651],[0.624,1.249],[1.873,4.37],[-0.624,4.995],[0,2.497],[-3.122,1.248],[-5.619,-9.989],[4.37,8.74],[-3.122,1.249],[-18.74,1.851],[0,0],[0,0],[0,0]],"o":[[-1.606,-4.283],[-14.988,-2.142],[0,0],[0,0],[0,0],[0,0],[0,0],[0,0],[-0.865,11.749],[2.667,1.251],[0.624,-0.624],[-3.746,-3.121],[-1.249,-4.371],[0.625,-2.497],[1.249,-3.746],[11.862,-4.995],[1.249,-10.614],[-1.873,-4.995],[17.572,-5.271],[-0.149,-1.533],[0,0],[0,0],[0,0]],"v":[[48.856,-34.001],[27.443,-44.707],[-32.512,-43.1],[-36.795,-47.918],[-41.077,-43.1],[-46.431,-47.918],[-44.825,-39.888],[-49.062,-44.171],[-49.597,-1.882],[-44.803,45.662],[-36.575,47.267],[-34.702,45.395],[-43.443,35.405],[-44.691,21.67],[-43.443,14.803],[-37.199,5.438],[-10.353,21.046],[-10.977,-9.546],[-12.85,-22.658],[42.135,-24.062],[41.896,-26.507],[46.179,-25.436],[42.432,-35.072]]}},"nm":"Path 1"},{"ty":"fl","fillEnabled":true,"c":{"k":[0,159,139,255]},"o":{"k":100},"nm":"Fill 1"},{"ty":"tr","p":{"k":[50.711,48.168]},"a":{"k":[0,0]},"s":{"k":[100,100]},"r":{"k":0},"o":{"k":100},"sk":{"k":0},"sa":{"k":0}}],"nm":"Group 9"}],"bounds":{"l":0,"t":0,"b":136,"r":100},"ip":0,"op":68.0000027696968,"st":0},{"ddd":0,"ind":1,"ty":4,"nm":"neck ","parent":5,"ks":{"o":{"k":100},"r":{"k":0},"p":{"k":[53.5,32.328,0]},"a":{"k":[25.3,93.521,0]},"s":{"k":[100,100,100]}},"shapes":[{"ty":"gr","it":[{"ind":0,"ty":"sh","closed":true,"ks":{"k":{"i":[[-0.033,0.004],[0,0],[11.324,0.868],[1.414,-9.227],[0.259,-4.513],[-17.336,-0.961],[0,0]],"o":[[0,0],[-1.726,-13.284],[-25.044,-1.919],[0.238,1.098],[11.737,11.386],[0,0],[0.033,-0.004]],"v":[[22.693,22.821],[21.274,5.788],[2.343,-21.968],[-21.958,-6.808],[-22.058,2.165],[22.701,23.887],[22.593,22.831]]}},"nm":"Path 1"},{"ty":"fl","fillEnabled":true,"c":{"k":[0,159,139,255]},"o":{"k":100},"nm":"Fill 1"},{"ty":"tr","p":{"k":[26.452,24.137]},"a":{"k":[0,0]},"s":{"k":[100,100]},"r":{"k":0},"o":{"k":100},"sk":{"k":0},"sa":{"k":0}}],"nm":"Group 1"},{"ty":"gr","it":[{"ind":0,"ty":"sh","closed":true,"ks":{"k":{"i":[[0,0],[-25.32,-11.075],[0,0],[0,0],[11.738,11.387]],"o":[[0,0],[25.32,11.075],[0,0],[-17.337,-0.961],[-0.858,14.916]],"v":[[-25.607,2.672],[-0.73,28.671],[26.05,13.191],[22.853,-18.022],[-21.907,-39.746]]}},"nm":"Path 1"},{"ty":"fl","fillEnabled":true,"c":{"k":[236,216,47,255]},"o":{"k":100},"nm":"Fill 1"},{"ty":"tr","p":{"k":[26.3,66.047]},"a":{"k":[0,0]},"s":{"k":[100,100]},"r":{"k":0},"o":{"k":100},"sk":{"k":0},"sa":{"k":0}}],"nm":"Group 2"}],"bounds":{"l":0,"t":1,"b":98,"r":53},"ip":0,"op":68.0000027696968,"st":0},{"ddd":0,"ind":2,"ty":4,"nm":"l_arm_upper ","parent":5,"ks":{"o":{"k":100},"r":{"k":[{"i":{"x":[0.667],"y":[1]},"o":{"x":[0.333],"y":[0]},"n":["0p667_1_0p333_0"],"t":0,"s":[0],"e":[-15]},{"i":{"x":[0.667],"y":[1]},"o":{"x":[0.333],"y":[0]},"n":["0p667_1_0p333_0"],"t":30,"s":[-15],"e":[0]},{"t":59.0000024031193}]},"p":{"k":[13.468,31.81,0]},"a":{"k":[56.519,34.686,0]},"s":{"k":[100,100,100]}},"shapes":[{"ty":"gr","it":[{"ind":0,"ty":"sh","closed":true,"ks":{"k":{"i":[[7.116,1.248],[0,0],[0,0],[0,0],[0,0]],"o":[[0,0],[0,0],[0,0],[0,0],[0,0]],"v":[[21.011,-55.673],[-9.502,-61.026],[-31.985,21.948],[8.814,61.026],[31.985,-28.907]]}},"nm":"Path 1"},{"ty":"fl","fillEnabled":true,"c":{"k":[0,159,139,255]},"o":{"k":100},"nm":"Fill 1"},{"ty":"tr","p":{"k":[52.804,61.276]},"a":{"k":[0,0]},"s":{"k":[100,100]},"r":{"k":0},"o":{"k":100},"sk":{"k":0},"sa":{"k":0}}],"nm":"Group 1"},{"ty":"gr","it":[{"ind":0,"ty":"sh","closed":true,"ks":{"k":{"i":[[0,0],[0,0],[0,0],[0,0],[-10.367,-1.547]],"o":[[0.955,-1.294],[0,0],[0,0],[-1.882,2.947],[17.022,2.541]],"v":[[4.088,39.145],[31.355,-40.362],[-8.645,-57.9],[-29.473,37.265],[-16.706,55.359]]}},"nm":"Path 1"},{"ty":"fl","fillEnabled":true,"c":{"k":[236,216,47,255]},"o":{"k":100},"nm":"Fill 1"},{"ty":"tr","p":{"k":[31.604,133.222]},"a":{"k":[0,0]},"s":{"k":[100,100]},"r":{"k":0},"o":{"k":100},"sk":{"k":0},"sa":{"k":0}}],"nm":"Group 2"}],"bounds":{"l":1,"t":0,"b":189,"r":85},"ip":0,"op":68.0000027696968,"st":0},{"ddd":0,"ind":3,"ty":4,"nm":"l_arm_lower ","parent":2,"ks":{"o":{"k":100},"r":{"k":[{"i":{"x":[0.667],"y":[1]},"o":{"x":[0.333],"y":[0]},"n":["0p667_1_0p333_0"],"t":0,"s":[15],"e":[0]},{"i":{"x":[0.667],"y":[1]},"o":{"x":[0.333],"y":[0]},"n":["0p667_1_0p333_0"],"t":15,"s":[0],"e":[-23]},{"i":{"x":[0.667],"y":[1]},"o":{"x":[0.333],"y":[0]},"n":["0p667_1_0p333_0"],"t":30,"s":[-23],"e":[15]},{"t":59.0000024031193}]},"p":{"k":[20.026,178.928,0]},"a":{"k":[18.195,21.037,0]},"s":{"k":[100,100,100]}},"shapes":[{"ty":"gr","it":[{"ind":0,"ty":"sh","closed":true,"ks":{"k":{"i":[[0,0],[0,0],[10.187,1.839],[1.862,-10.315],[0.037,-0.852],[0,0],[-2.122,-12.35],[-8.283,0.681]],"o":[[0,0],[-0.267,-10.921],[-10.315,-1.862],[-0.156,0.863],[0,0],[0,0],[2.122,12.35],[8.282,-0.681]],"v":[[18.735,47.308],[18.945,-42.225],[3.028,-61.925],[-18.469,-48.584],[-18.751,-46.011],[-18.945,-45.545],[-9.617,51.438],[8.925,62.52]]}},"nm":"Path 1"},{"ty":"fl","fillEnabled":true,"c":{"k":[236,216,47,255]},"o":{"k":100},"nm":"Fill 1"},{"ty":"tr","p":{"k":[19.195,64.038]},"a":{"k":[0,0]},"s":{"k":[100,100]},"r":{"k":0},"o":{"k":100},"sk":{"k":0},"sa":{"k":0}}],"nm":"Group 1"}],"bounds":{"l":0,"t":1,"b":127,"r":39},"ip":0,"op":68.0000027696968,"st":0},{"ddd":0,"ind":4,"ty":4,"nm":"l_hand ","parent":3,"ks":{"o":{"k":100},"r":{"k":-21},"p":{"k":[22.546,120.426,0]},"a":{"k":[25.157,21.827,0]},"s":{"k":[100,100,100]}},"shapes":[{"ty":"gr","it":[{"ind":0,"ty":"sh","closed":true,"ks":{"k":{"i":[[3.659,9.408],[0,0],[3.322,-16.293],[0.817,-6.656],[-2.487,-3.396],[-3.906,2.171],[-3.584,3.86]],"o":[[-3.659,-9.408],[0,0],[-1.341,6.572],[-0.461,3.748],[3.512,4.794],[4.621,-2.568],[15.977,-17.207]],"v":[[17.829,-32.169],[-7.174,-27.557],[-16.268,4.48],[-19.383,24.352],[-19.419,36.783],[-6.333,35.87],[5.929,25.913]]}},"nm":"Path 1"},{"ty":"fl","fillEnabled":true,"c":{"k":[236,216,47,255]},"o":{"k":100},"nm":"Fill 1"},{"ty":"tr","p":{"k":[22.156,41.827]},"a":{"k":[0,0]},"s":{"k":[100,100]},"r":{"k":0},"o":{"k":100},"sk":{"k":0},"sa":{"k":0}}],"nm":"Group 1"}],"bounds":{"l":1,"t":6,"b":82,"r":43},"ip":0,"op":68.0000027696968,"st":0},{"ddd":0,"ind":5,"ty":4,"nm":"shirt ","parent":6,"ks":{"o":{"k":100},"r":{"k":0},"p":{"k":[44.682,-75.214,0]},"a":{"k":[41.737,104.002,0]},"s":{"k":[100,100,100]}},"shapes":[{"ty":"gr","it":[{"ind":0,"ty":"sh","closed":true,"ks":{"k":{"i":[[0,0],[0,0],[10.089,-2.478],[0,0],[0,0],[-5.889,-26.765],[0,0],[-26.765,-0.536],[0,0],[0,0]],"o":[[0,0],[0,0],[0,0],[0,0],[0,0],[5.888,26.766],[0,0],[26.766,0.535],[0,0],[0,0]],"v":[[38.384,-86.295],[31.316,-94.85],[-10.974,-101.273],[-14.062,-100.515],[-41.487,-93.78],[-32.921,22.384],[-26.23,89.298],[7.762,103.216],[38.813,94.323],[41.487,-82.538]]}},"nm":"Path 1"},{"ty":"fl","fillEnabled":true,"c":{"k":[0,159,139,255]},"o":{"k":100},"nm":"Fill 1"},{"ty":"tr","p":{"k":[41.737,104.002]},"a":{"k":[0,0]},"s":{"k":[100,100]},"r":{"k":0},"o":{"k":100},"sk":{"k":0},"sa":{"k":0}}],"nm":"Group 1"}],"bounds":{"l":0,"t":2,"b":208,"r":84},"ip":0,"op":68.0000027696968,"st":0},{"ddd":0,"ind":6,"ty":4,"nm":"pants ","ks":{"o":{"k":100},"r":{"k":0},"p":{"k":[{"i":{"x":0.667,"y":1},"o":{"x":0.333,"y":0},"n":"0p667_1_0p333_0","t":0,"s":[287.405,427.181,0],"e":[287.405,421.181,0],"to":[0,0,0],"ti":[0,0,0]},{"i":{"x":0.667,"y":1},"o":{"x":0.333,"y":0},"n":"0p667_1_0p333_0","t":15,"s":[287.405,421.181,0],"e":[287.405,427.181,0],"to":[0,0,0],"ti":[0,0,0]},{"i":{"x":0.667,"y":1},"o":{"x":0.333,"y":0},"n":"0p667_1_0p333_0","t":30,"s":[287.405,427.181,0],"e":[287.405,421.181,0],"to":[0,0,0],"ti":[0,0,0]},{"i":{"x":0.667,"y":1},"o":{"x":0.333,"y":0},"n":"0p667_1_0p333_0","t":46,"s":[287.405,421.181,0],"e":[287.405,427.181,0],"to":[0,0,0],"ti":[0,0,0]},{"t":59.0000024031193}]},"a":{"k":[51.381,44.791,0]},"s":{"k":[100,100,100]}},"shapes":[{"ty":"gr","it":[{"ind":0,"ty":"sh","closed":true,"ks":{"k":{"i":[[-1.065,-8.894],[-0.235,-1.488],[-20.31,-7.144],[-5.187,22.598],[2.521,11.556],[1.876,8.6],[0.067,0],[29.445,1.64],[9.256,-8.653],[1.158,-2.216]],"o":[[0.245,2.046],[3.221,20.392],[23.971,8.43],[2.774,-12.085],[-1.876,-8.601],[-0.023,-0.106],[-0.002,-0.001],[-13.128,-0.732],[-1.193,1.115],[-4.238,8.113]],"v":[[-45.066,-3.099],[-44.311,2.283],[-6.456,53.111],[43.357,18.247],[42.53,-14.997],[37.526,-40.799],[37.115,-42.682],[7.67,-60.809],[-27.928,-47.707],[-41.679,-27.615]]}},"nm":"Path 1"},{"ty":"fl","fillEnabled":true,"c":{"k":[201,255,45,255]},"o":{"k":100},"nm":"Fill 1"},{"ty":"tr","p":{"k":[46.381,61.792]},"a":{"k":[0,0]},"s":{"k":[100,100]},"r":{"k":0},"o":{"k":100},"sk":{"k":0},"sa":{"k":0}}],"nm":"Group 1"}],"bounds":{"l":0,"t":0,"b":117,"r":92},"ip":0,"op":68.0000027696968,"st":0},{"ddd":0,"ind":7,"ty":4,"nm":"l_leg_upper ","ks":{"o":{"k":100},"r":{"k":[{"i":{"x":[0.667],"y":[1]},"o":{"x":[0.333],"y":[0]},"n":["0p667_1_0p333_0"],"t":0,"s":[-20],"e":[0]},{"i":{"x":[0.667],"y":[1]},"o":{"x":[0.333],"y":[0]},"n":["0p667_1_0p333_0"],"t":15,"s":[0],"e":[2]},{"i":{"x":[0.667],"y":[-2.446]},"o":{"x":[0.333],"y":[0]},"n":["0p667_-2p446_0p333_0"],"t":30,"s":[2],"e":[0.504]},{"i":{"x":[0.667],"y":[1]},"o":{"x":[0.333],"y":[0.204]},"n":["0p667_1_0p333_0p204"],"t":46,"s":[0.504],"e":[-20]},{"t":59.0000024031193}]},"p":{"k":[255.216,445.685,0]},"a":{"k":[32.467,31.885,0]},"s":{"k":[100,100,100]}},"shapes":[{"ty":"gr","it":[{"ind":0,"ty":"sh","closed":true,"ks":{"k":{"i":[[-0.472,19],[19.789,4.494],[0,0],[0,0],[0,0]],"o":[[0,0],[-26.424,-6.001],[0,0],[0,0],[0,0]],"v":[[29.129,-41.163],[11.428,-69.279],[-17.416,-59.219],[-31.217,55.804],[29.376,75.279]]}},"nm":"Path 1"},{"ty":"fl","fillEnabled":true,"c":{"k":[201,255,45,255]},"o":{"k":100},"nm":"Fill 1"},{"ty":"tr","p":{"k":[31.467,75.53]},"a":{"k":[0,0]},"s":{"k":[100,100]},"r":{"k":0},"o":{"k":100},"sk":{"k":0},"sa":{"k":0}}],"nm":"Group 1"},{"ty":"gr","it":[{"ind":0,"ty":"sh","closed":true,"ks":{"k":{"i":[[0,0],[0,0],[-17.844,0.258],[0,0],[0,0]],"o":[[-0.535,2.677],[0,0],[16.28,-0.236],[0,0],[0,0]],"v":[[-22.885,-48.706],[-18.067,32.126],[2.728,48.448],[23.42,33.732],[23.42,-48.706]]}},"nm":"Path 1"},{"ty":"fl","fillEnabled":true,"c":{"k":[236,216,47,255]},"o":{"k":100},"nm":"Fill 1"},{"ty":"tr","p":{"k":[34.539,166.815]},"a":{"k":[0,0]},"s":{"k":[100,100]},"r":{"k":0},"o":{"k":100},"sk":{"k":0},"sa":{"k":0}}],"nm":"Group 2"}],"bounds":{"l":0,"t":4,"b":216,"r":61},"ip":0,"op":68.0000027696968,"st":0},{"ddd":0,"ind":8,"ty":4,"nm":"l_leg_lower ","parent":7,"ks":{"o":{"k":100},"r":{"k":[{"i":{"x":[0.667],"y":[0.667]},"o":{"x":[0.333],"y":[0.333]},"n":["0p667_0p667_0p333_0p333"],"t":0,"s":[0],"e":[0]},{"i":{"x":[0.667],"y":[0.659]},"o":{"x":[0.333],"y":[0]},"n":["0p667_0p659_0p333_0"],"t":15,"s":[0],"e":[21.274]},{"i":{"x":[0.667],"y":[1]},"o":{"x":[0.333],"y":[0.886]},"n":["0p667_1_0p333_0p886"],"t":30,"s":[21.274],"e":[30]},{"i":{"x":[0.667],"y":[0.281]},"o":{"x":[0.333],"y":[0]},"n":["0p667_0p281_0p333_0"],"t":46,"s":[30],"e":[16.22]},{"i":{"x":[0.667],"y":[1]},"o":{"x":[0.333],"y":[0.382]},"n":["0p667_1_0p333_0p382"],"t":54,"s":[16.22],"e":[0]},{"t":59.0000024031193}]},"p":{"k":[40.322,212.947,0]},"a":{"k":[49.998,22.603,0]},"s":{"k":[100,100,100]}},"shapes":[{"ty":"gr","it":[{"ind":0,"ty":"sh","closed":true,"ks":{"k":{"i":[[-7.984,4.283],[4.331,-16.218],[0,0],[12.749,1.249],[0,0],[-1.07,6.959]],"o":[[0,0],[-4.331,16.218],[0,0],[-12.75,-1.248],[0,0],[1.071,-6.959]],"v":[[10.537,-102.289],[31.417,-90.134],[-6.103,99.525],[-22.998,105.104],[-35.748,96.609],[-26.981,-53.04]]}},"nm":"Path 1"},{"ty":"fl","fillEnabled":true,"c":{"k":[236,216,47,255]},"o":{"k":100},"nm":"Fill 1"},{"ty":"tr","p":{"k":[35.998,106.603]},"a":{"k":[0,0]},"s":{"k":[100,100]},"r":{"k":0},"o":{"k":100},"sk":{"k":0},"sa":{"k":0}}],"nm":"Group 1"}],"bounds":{"l":0,"t":3,"b":212,"r":68},"ip":0,"op":68.0000027696968,"st":0},{"ddd":0,"ind":9,"ty":4,"nm":"l_foot ","parent":8,"ks":{"o":{"k":100},"r":{"k":[{"i":{"x":[0.667],"y":[1]},"o":{"x":[0.333],"y":[0]},"n":["0p667_1_0p333_0"],"t":0,"s":[24],"e":[0]},{"i":{"x":[0.667],"y":[1]},"o":{"x":[0.333],"y":[0]},"n":["0p667_1_0p333_0"],"t":15,"s":[0],"e":[-24]},{"i":{"x":[0.667],"y":[1]},"o":{"x":[0.333],"y":[0]},"n":["0p667_1_0p333_0"],"t":30,"s":[-24],"e":[15]},{"i":{"x":[0.667],"y":[1]},"o":{"x":[0.333],"y":[0]},"n":["0p667_1_0p333_0"],"t":46,"s":[15],"e":[24]},{"t":59.0000024031193}]},"p":{"k":[13.608,200.678,0]},"a":{"k":[29.399,11.99,0]},"s":{"k":[100,100,100]}},"shapes":[{"ty":"gr","it":[{"ind":0,"ty":"sh","closed":true,"ks":{"k":{"i":[[0,0],[-36.936,6.424],[-1.754,3.658],[14.201,9.231],[0,0],[5.888,1.07],[2.141,-12.313]],"o":[[0,0],[12.44,-2.164],[3.455,-7.203],[-21.412,-13.918],[0,0],[-5.889,-1.071],[-2.142,12.312]],"v":[[-51.15,17.933],[21.296,31.316],[47.695,21.145],[17.549,-3.48],[-9.217,-27.569],[-18.852,-35.598],[-35.982,-25.427]]}},"nm":"Path 1"},{"ty":"fl","fillEnabled":true,"c":{"k":[236,216,47,255]},"o":{"k":100},"nm":"Fill 1"},{"ty":"tr","p":{"k":[51.399,37.99]},"a":{"k":[0,0]},"s":{"k":[100,100]},"r":{"k":0},"o":{"k":100},"sk":{"k":0},"sa":{"k":0}}],"nm":"Group 1"}],"bounds":{"l":0,"t":1,"b":71,"r":100},"ip":0,"op":68.0000027696968,"st":0},{"ddd":0,"ind":10,"ty":4,"nm":"r_leg_upper ","ks":{"o":{"k":100},"r":{"k":[{"i":{"x":[0.833],"y":[1]},"o":{"x":[0.333],"y":[0]},"n":["0p833_1_0p333_0"],"t":0,"s":[11],"e":[14]},{"i":{"x":[0.667],"y":[1]},"o":{"x":[0.333],"y":[0]},"n":["0p667_1_0p333_0"],"t":14,"s":[14],"e":[-20]},{"i":{"x":[0.667],"y":[1]},"o":{"x":[0.333],"y":[0]},"n":["0p667_1_0p333_0"],"t":29,"s":[-20],"e":[0.14]},{"i":{"x":[0.667],"y":[1]},"o":{"x":[0.333],"y":[0]},"n":["0p667_1_0p333_0"],"t":44,"s":[0.14],"e":[11]},{"i":{"x":[0.667],"y":[1]},"o":{"x":[0.333],"y":[0]},"n":["0p667_1_0p333_0"],"t":59,"s":[11],"e":[14]},{"t":73.000002973351}]},"p":{"k":[305.581,465.218,0]},"a":{"k":[24.022,31.773,0]},"s":{"k":[100,100,100]}},"shapes":[{"ty":"gr","it":[{"ind":0,"ty":"sh","closed":true,"ks":{"k":{"i":[[4.836,27.781],[7.322,-3.698],[3.49,-7.501],[0.844,-2.534],[0,0],[0,0]],"o":[[-1.799,-2.797],[-7.573,3.825],[-1.06,2.279],[0,0],[0,0],[0,0]],"v":[[14.296,-55.254],[-12.244,-61.759],[-28.202,-42.889],[-31.129,-35.628],[-22.863,65.457],[31.129,43.329]]}},"nm":"Path 1"},{"ty":"fl","fillEnabled":true,"c":{"k":[201,255,45,255]},"o":{"k":100},"nm":"Fill 1"},{"ty":"tr","p":{"k":[31.379,65.707]},"a":{"k":[0,0]},"s":{"k":[100,100]},"r":{"k":0},"o":{"k":100},"sk":{"k":0},"sa":{"k":0}}],"nm":"Group 1"},{"ty":"gr","it":[{"ind":0,"ty":"sh","closed":true,"ks":{"k":{"i":[[-12.848,-31.584],[-17.13,3.211],[1.606,20.877],[0,0],[0,0]],"o":[[0,0],[17.13,-3.212],[-1.606,-20.878],[0,0],[0,0]],"v":[[-9.368,57.52],[10.286,65.602],[27.033,39.855],[9.074,-68.814],[-28.639,-60.785]]}},"nm":"Path 1"},{"ty":"fl","fillEnabled":true,"c":{"k":[234,189,47,255]},"o":{"k":100},"nm":"Fill 1"},{"ty":"tr","p":{"k":[37.155,132.482]},"a":{"k":[0,0]},"s":{"k":[100,100]},"r":{"k":0},"o":{"k":100},"sk":{"k":0},"sa":{"k":0}}],"nm":"Group 2"}],"bounds":{"l":0,"t":2,"b":199,"r":65},"ip":0,"op":68.0000027696968,"st":0},{"ddd":0,"ind":11,"ty":4,"nm":"r_leg_lower ","parent":10,"ks":{"o":{"k":100},"r":{"k":[{"i":{"x":[0.833],"y":[0.833]},"o":{"x":[0.167],"y":[0.167]},"n":["0p833_0p833_0p167_0p167"],"t":0,"s":[23],"e":[23]},{"i":{"x":[0.667],"y":[1]},"o":{"x":[0.333],"y":[0]},"n":["0p667_1_0p333_0"],"t":14,"s":[23],"e":[-4]},{"i":{"x":[0.667],"y":[1]},"o":{"x":[0.333],"y":[0]},"n":["0p667_1_0p333_0"],"t":29,"s":[-4],"e":[0]},{"i":{"x":[0.667],"y":[1]},"o":{"x":[0.333],"y":[0]},"n":["0p667_1_0p333_0"],"t":46,"s":[0],"e":[23]},{"t":59.0000024031193}]},"p":{"k":[49.594,197.379,0]},"a":{"k":[41.328,18.457,0]},"s":{"k":[100,100,100]}},"shapes":[{"ty":"gr","it":[{"ind":0,"ty":"sh","closed":true,"ks":{"k":{"i":[[-2.135,-3.99],[0,0],[10.171,0.536],[0,0],[-8.565,12.312],[0,0],[-7.332,1.604]],"o":[[0,0],[0,0],[-10.171,-0.535],[0,0],[8.565,-12.312],[0,0],[5.724,-1.253]],"v":[[28.078,-86.659],[4.9,84.221],[-9.342,92.671],[-22.19,83.036],[-19.513,-59.357],[-0.188,-84.129],[12.319,-91.954]]}},"nm":"Path 1"},{"ty":"fl","fillEnabled":true,"c":{"k":[234,189,47,255]},"o":{"k":100},"nm":"Fill 1"},{"ty":"tr","p":{"k":[28.328,93.458]},"a":{"k":[0,0]},"s":{"k":[100,100]},"r":{"k":0},"o":{"k":100},"sk":{"k":0},"sa":{"k":0}}],"nm":"Group 1"}],"bounds":{"l":4,"t":1,"b":187,"r":57},"ip":0,"op":68.0000027696968,"st":0},{"ddd":0,"ind":12,"ty":4,"nm":"r_foot ","parent":11,"ks":{"o":{"k":100},"r":{"k":[{"i":{"x":[0.833],"y":[1]},"o":{"x":[0.333],"y":[0]},"n":["0p833_1_0p333_0"],"t":0,"s":[-25],"e":[11]},{"i":{"x":[0.667],"y":[1]},"o":{"x":[0.333],"y":[0]},"n":["0p667_1_0p333_0"],"t":14,"s":[11],"e":[24]},{"i":{"x":[0.667],"y":[1]},"o":{"x":[0.333],"y":[0]},"n":["0p667_1_0p333_0"],"t":29,"s":[24],"e":[-0.013]},{"i":{"x":[0.667],"y":[1]},"o":{"x":[0.333],"y":[0]},"n":["0p667_1_0p333_0"],"t":46,"s":[-0.013],"e":[-25]},{"t":59.0000024031193}]},"p":{"k":[19.539,176.198,0]},"a":{"k":[29.875,20.401,0]},"s":{"k":[100,100,100]}},"shapes":[{"ty":"gr","it":[{"ind":0,"ty":"sh","closed":true,"ks":{"k":{"i":[[0.006,-0.024],[0.532,-0.309],[0,0],[-30.28,-0.889],[-6.466,4.433],[6.631,5.154],[10.734,17.122]],"o":[[-0.131,0.523],[-10.008,5.811],[0,0],[15.957,0.469],[-3.174,-7.017],[-14.619,-11.36],[-10.133,-16.164]],"v":[[-27.549,-17.987],[-32.361,-15.575],[-51.625,24.109],[14.867,33.682],[51.625,26.456],[38.646,10.294],[-9.056,-17.987]]}},"nm":"Path 1"},{"ty":"fl","fillEnabled":true,"c":{"k":[234,189,47,255]},"o":{"k":100},"nm":"Fill 1"},{"ty":"tr","p":{"k":[51.875,34.401]},"a":{"k":[0,0]},"s":{"k":[100,100]},"r":{"k":0},"o":{"k":100},"sk":{"k":0},"sa":{"k":0}}],"nm":"Group 1"}],"bounds":{"l":0,"t":9,"b":69,"r":104},"ip":-1.00000004073083,"op":69.0000028104276,"st":1.00000004073083},{"ddd":0,"ind":13,"ty":4,"nm":"r_arm_upper ","parent":5,"ks":{"o":{"k":100},"r":{"k":[{"i":{"x":[0.667],"y":[1]},"o":{"x":[0.333],"y":[0]},"n":["0p667_1_0p333_0"],"t":0,"s":[-6],"e":[18]},{"i":{"x":[0.667],"y":[1]},"o":{"x":[0.333],"y":[0]},"n":["0p667_1_0p333_0"],"t":30,"s":[18],"e":[-6]},{"t":59.0000024031193}]},"p":{"k":[62.477,27.012,0]},"a":{"k":[11.621,19.09,0]},"s":{"k":[100,100,100]}},"shapes":[{"ty":"gr","it":[{"ind":0,"ty":"sh","closed":true,"ks":{"k":{"i":[[0,0],[0,0],[-1.071,-2.141],[0,0]],"o":[[0,0],[0,0],[1.07,2.141],[0,0]],"v":[[-28.371,-55.627],[12.848,-53.042],[27.301,33.679],[-22.484,55.627]]}},"nm":"Path 1"},{"ty":"fl","fillEnabled":true,"c":{"k":[0,159,139,255]},"o":{"k":100},"nm":"Fill 1"},{"ty":"tr","p":{"k":[28.621,55.877]},"a":{"k":[0,0]},"s":{"k":[100,100]},"r":{"k":0},"o":{"k":100},"sk":{"k":0},"sa":{"k":0}}],"nm":"Group 1"},{"ty":"gr","it":[{"ind":0,"ty":"sh","closed":true,"ks":{"k":{"i":[[0,0],[0,0],[11.273,10.703],[0,0]],"o":[[1.606,1.606],[0,0],[-6.991,-12.309],[0,0]],"v":[[5.873,-44.428],[15.508,30.516],[-7.479,40.149],[-15.508,-50.852]]}},"nm":"Path 1"},{"ty":"fl","fillEnabled":true,"c":{"k":[234,189,47,255]},"o":{"k":100},"nm":"Fill 1"},{"ty":"tr","p":{"k":[33.991,129.077]},"a":{"k":[0,0]},"s":{"k":[100,100]},"r":{"k":0},"o":{"k":100},"sk":{"k":0},"sa":{"k":0}}],"nm":"Group 2"}],"bounds":{"l":0,"t":0,"b":173,"r":56},"ip":0,"op":68.0000027696968,"st":0},{"ddd":0,"ind":14,"ty":4,"nm":"r_arm_lower ","parent":13,"ks":{"o":{"k":100},"r":{"k":[{"i":{"x":[0.667],"y":[1]},"o":{"x":[0.333],"y":[0]},"n":["0p667_1_0p333_0"],"t":0,"s":[-14],"e":[14]},{"i":{"x":[0.667],"y":[1]},"o":{"x":[0.333],"y":[0]},"n":["0p667_1_0p333_0"],"t":30,"s":[14],"e":[-14]},{"t":59.0000024031193}]},"p":{"k":[36.271,166.668,0]},"a":{"k":[13.094,12.346,0]},"s":{"k":[100,100,100]}},"shapes":[{"ty":"gr","it":[{"ind":0,"ty":"sh","closed":true,"ks":{"k":{"i":[[0,0],[0,0],[5.725,-4.794],[0.552,0.312],[0,0]],"o":[[0,0],[0,0],[-4.421,3.703],[-1.266,-0.715],[0,0]],"v":[[1.245,-55.097],[23.305,39.251],[18.12,51.394],[2.228,52.235],[-23.844,-49.23]]}},"nm":"Path 1"},{"ty":"fl","fillEnabled":true,"c":{"k":[234,189,47,255]},"o":{"k":100},"nm":"Fill 1"},{"ty":"tr","p":{"k":[24.094,55.346]},"a":{"k":[0,0]},"s":{"k":[100,100]},"r":{"k":0},"o":{"k":100},"sk":{"k":0},"sa":{"k":0}}],"nm":"Group 1"}],"bounds":{"l":0,"t":0,"b":109,"r":48},"ip":0,"op":68.0000027696968,"st":0},{"ddd":0,"ind":15,"ty":4,"nm":"r_hand ","parent":14,"ks":{"o":{"k":100},"r":{"k":-20},"p":{"k":[36.882,101.877,0]},"a":{"k":[22.89,16.748,0]},"s":{"k":[100,100,100]}},"shapes":[{"ty":"gr","it":[{"ind":0,"ty":"sh","closed":true,"ks":{"k":{"i":[[-31.253,6.541],[5.359,-22.409],[0,0]],"o":[[0,0],[-5.689,23.791],[0,0]],"v":[[10.613,-37.498],[15.281,7.782],[-15.583,37.498]]}},"nm":"Path 1"},{"ty":"fl","fillEnabled":true,"c":{"k":[234,189,47,255]},"o":{"k":100},"nm":"Fill 1"},{"ty":"tr","p":{"k":[20.89,37.748]},"a":{"k":[0,0]},"s":{"k":[100,100]},"r":{"k":0},"o":{"k":100},"sk":{"k":0},"sa":{"k":0}}],"nm":"Group 1"}],"bounds":{"l":5,"t":0,"b":76,"r":38},"ip":0,"op":68.0000027696968,"st":0}]}],"v":"4.1.7","ddd":0,"layers":[{"ddd":0,"ind":0,"ty":0,"nm":"Character_color","refId":"comp_2","ks":{"o":{"k":100},"r":{"k":0},"p":{"k":[224,354,0]},"a":{"k":[284,450,0]},"s":{"k":[80.282,80.282,100]}},"w":568,"h":900,"ip":0,"op":97.5000039712564,"st":0}],"ip":0,"op":39.0000015885026,"fr":29.9700012207031,"w":448,"h":708}